setup.py
clean_folder_homework_by_egor/__init__.py
clean_folder_homework_by_egor/clean.py
clean_folder_homework_by_egor.egg-info/PKG-INFO
clean_folder_homework_by_egor.egg-info/SOURCES.txt
clean_folder_homework_by_egor.egg-info/dependency_links.txt
clean_folder_homework_by_egor.egg-info/entry_points.txt
clean_folder_homework_by_egor.egg-info/top_level.txt