Metadata-Version: 2.1
Name: clean-folder-homework-by-egor
Version: 1.0.0
Summary: homework
Home-page: UNKNOWN
License: UNKNOWN
Platform: UNKNOWN
